property_completeness
