Metadata-Version: 1.1
Name: property-completeness
Version: 0.0.5
Summary: compute property completeness
Home-page: UNKNOWN
Author: Rex Sang
Author-email: rex@enodoinc.com
License: BSD
Platform: UNKNOWN
Classifier: Development Status :: 3 - Alpha
Classifier: Intended Audience :: Developers
Classifier: Programming Language :: Python :: 2.7
